README.md
setup.cfg
setup.py
pydaptivefiltering/Meta_LMS.py
pydaptivefiltering/__init__.py
pydaptivefiltering/main.py
pydaptivefiltering.egg-info/PKG-INFO
pydaptivefiltering.egg-info/SOURCES.txt
pydaptivefiltering.egg-info/dependency_links.txt
pydaptivefiltering.egg-info/requires.txt
pydaptivefiltering.egg-info/top_level.txt
pydaptivefiltering/LMS/LMS.py
pydaptivefiltering/LMS/LMS_Newton.py
pydaptivefiltering/LMS/NLMS.py
pydaptivefiltering/LMS/SignData.py
pydaptivefiltering/LMS/SignError.py
pydaptivefiltering/LMS/__init__.py
pydaptivefiltering/RLS/RLS.py
pydaptivefiltering/RLS/RLS_Alt.py
pydaptivefiltering/RLS/__init__.py
pydaptivefiltering/SM/AP.py
pydaptivefiltering/SM/NLMS.py
pydaptivefiltering/SM/__init__.py