Metadata-Version: 1.1
Name: pydaptivefiltering
Version: 0.3
Summary:  Python 3.8+ Implementation of the AdaptiveFiltering Toolbox.
Home-page: https://github.com/BruninLima
Author: Bruno Lima Netto
Author-email: brunolimanetto@gmail.com
License: UNKNOWN
Download-URL: https://github.com/BruninLima/PydaptiveFiltering/archive/refs/tags/v0.3.tar.gz
Keywords: Adaptive,Filtering,Digital,Signal,Processing
Platform: UNKNOWN
Classifier: Development Status :: 3 - Alpha
Classifier: Intended Audience :: Science/Research
Classifier: Topic :: Software Development :: Libraries
Classifier: Programming Language :: Python :: 3
